strec/__init__.py
strec/calc.py
strec/cmt.py
strec/config.py
strec/database.py
strec/distance.py
strec/gcmt.py
strec/gmreg.py
strec/kagan.py
strec/slab.py
strec/sm_probs.py
strec/subduction.py
strec/subtype.py
strec/utils.py
strec/bin/regcalc.py
strec/bin/strec_cfg.py
strec/data/REGION_GRIDS_README.txt
strec/data/__init__.py
strec/data/active.geojson
strec/data/backarc.geojson
strec/data/domains.xlsx
strec/data/land.geojson
strec/data/maximum_interface_depths.csv
strec/data/moment_tensors.db
strec/data/ocean.geojson
strec/data/select.conf
strec/data/selectspec.conf
strec/data/stable.geojson
strec/data/strec.ini
strec/data/subduction.geojson
strec/data/volcanic.geojson
usgs_strec-2.3.13.dist-info/licenses/LICENSE.md
usgs_strec-2.3.13.dist-info/METADATA
usgs_strec-2.3.13.dist-info/WHEEL
usgs_strec-2.3.13.dist-info/entry_points.txt
usgs_strec-2.3.13.dist-info/top_level.txt
usgs_strec-2.3.13.dist-info/RECORD
