Metadata-Version: 2.4
Name: usgs-strec
Version: 2.3.13
Summary: USGS SeismoTectonic Regime Earthquake Calculator (STREC)
Author-email: Mike Hearne <mhearne@usgs.gov>, Eric Thompson <ethompson@usgs.gov>
License-Expression: CC0-1.0
Keywords: comcat,earthquake
Requires-Python: >=3.8
License-File: LICENSE.md
Requires-Dist: configobj>=5.0.6
Requires-Dist: esi-utils-rupture
Requires-Dist: geopandas
Requires-Dist: geopy>=2.2.0
Requires-Dist: numpy>=1.21.0
Requires-Dist: openpyxl>=3.0.9
Requires-Dist: pandas>=1.3.5
Requires-Dist: rasterio>=1.2.10
Requires-Dist: sciencebasepy>=2.0.16
Requires-Dist: xlrd>=2.0.1
Requires-Dist: xlsxwriter>=3.0.1
Requires-Dist: xlwt>=1.3.0
Provides-Extra: dev
Requires-Dist: build>=0.7.0; extra == "dev"
Requires-Dist: black>=21; extra == "dev"
Requires-Dist: flake8>=3.9; extra == "dev"
Requires-Dist: ipython>=7.26; extra == "dev"
Requires-Dist: notebook>=6.4.1; extra == "dev"
Provides-Extra: test
Requires-Dist: pytest>=6.2; extra == "test"
Requires-Dist: pytest-cov>=2.12.0; extra == "test"
Provides-Extra: build
Requires-Dist: build; extra == "build"
Requires-Dist: twine; extra == "build"
Requires-Dist: check-wheel-contents; extra == "build"
Dynamic: license-file
